[
  {
    "id": 1,
    "name": "Puanteur"
  },
  {
    "id": 2,
    "name": "Crachin"
  },
  {
    "id": 3,
    "name": "Turbo"
  },
  {
    "id": 4,
    "name": "Armurbaston"
  },
  {
    "id": 5,
    "name": "Fermeté"
  },
  {
    "id": 6,
    "name": "Moiteur"
  },
  {
    "id": 7,
    "name": "Échauffement"
  },
  {
    "id": 8,
    "name": "Voile Sable"
  },
  {
    "id": 9,
    "name": "Statik"
  },
  {
    "id": 10,
    "name": "Absorbe-Volt"
  },
  {
    "id": 11,
    "name": "Absorbe-Eau"
  },
  {
    "id": 12,
    "name": "Benêt"
  },
  {
    "id": 13,
    "name": "Ciel Gris"
  },
  {
    "id": 14,
    "name": "Œil Composé"
  },
  {
    "id": 15,
    "name": "Insomnia"
  },
  {
    "id": 16,
    "name": "Homochromie"
  },
  {
    "id": 17,
    "name": "Vaccin"
  },
  {
    "id": 18,
    "name": "Torche"
  },
  {
    "id": 19,
    "name": "Écran Poudre"
  },
  {
    "id": 20,
    "name": "Tempo Perso"
  },
  {
    "id": 21,
    "name": "Ventouse"
  },
  {
    "id": 22,
    "name": "Intimidation"
  },
  {
    "id": 23,
    "name": "Marque Ombre"
  },
  {
    "id": 24,
    "name": "Peau Dure"
  },
  {
    "id": 25,
    "name": "Garde Mystik"
  },
  {
    "id": 26,
    "name": "Lévitation"
  },
  {
    "id": 27,
    "name": "Pose Spore"
  },
  {
    "id": 28,
    "name": "Synchro"
  },
  {
    "id": 29,
    "name": "Corps Sain"
  },
  {
    "id": 30,
    "name": "Médic Nature"
  },
  {
    "id": 31,
    "name": "Paratonnerre"
  },
  {
    "id": 32,
    "name": "Sérénité"
  },
  {
    "id": 33,
    "name": "Glissade"
  },
  {
    "id": 34,
    "name": "Chlorophylle"
  },
  {
    "id": 35,
    "name": "Lumiattirance"
  },
  {
    "id": 36,
    "name": "Calque"
  },
  {
    "id": 37,
    "name": "Coloforce"
  },
  {
    "id": 38,
    "name": "Point Poison"
  },
  {
    "id": 39,
    "name": "Attention"
  },
  {
    "id": 40,
    "name": "Armumagma"
  },
  {
    "id": 41,
    "name": "Ignifu-Voile"
  },
  {
    "id": 42,
    "name": "Magnépiège"
  },
  {
    "id": 43,
    "name": "Anti-Bruit"
  },
  {
    "id": 44,
    "name": "Cuvette"
  },
  {
    "id": 45,
    "name": "Sable Volant"
  },
  {
    "id": 46,
    "name": "Pression"
  },
  {
    "id": 47,
    "name": "Isograisse"
  },
  {
    "id": 48,
    "name": "Matinal"
  },
  {
    "id": 49,
    "name": "Corps Ardent"
  },
  {
    "id": 50,
    "name": "Fuite"
  },
  {
    "id": 51,
    "name": "Regard Vif"
  },
  {
    "id": 52,
    "name": "Hyper Cutter"
  },
  {
    "id": 53,
    "name": "Ramassage"
  },
  {
    "id": 54,
    "name": "Absentéisme"
  },
  {
    "id": 55,
    "name": "Agitation"
  },
  {
    "id": 56,
    "name": "Joli Sourire"
  },
  {
    "id": 57,
    "name": "Plus"
  },
  {
    "id": 58,
    "name": "Moins"
  },
  {
    "id": 59,
    "name": "Météo"
  },
  {
    "id": 60,
    "name": "Glu"
  },
  {
    "id": 61,
    "name": "Mue"
  },
  {
    "id": 62,
    "name": "Cran"
  },
  {
    "id": 63,
    "name": "Écaille Spéciale"
  },
  {
    "id": 64,
    "name": "Suintement"
  },
  {
    "id": 65,
    "name": "Engrais"
  },
  {
    "id": 66,
    "name": "Brasier"
  },
  {
    "id": 67,
    "name": "Torrent"
  },
  {
    "id": 68,
    "name": "Essaim"
  },
  {
    "id": 69,
    "name": "Tête de Roc"
  },
  {
    "id": 70,
    "name": "Sécheresse"
  },
  {
    "id": 71,
    "name": "Piège Sable"
  },
  {
    "id": 72,
    "name": "Esprit Vital"
  },
  {
    "id": 73,
    "name": "Écran Fumée"
  },
  {
    "id": 74,
    "name": "Force Pure"
  },
  {
    "id": 75,
    "name": "Coque Armure"
  },
  {
    "id": 76,
    "name": "Air Lock"
  },
  {
    "id": 77,
    "name": "Pieds Confus"
  },
  {
    "id": 78,
    "name": "Motorisé"
  },
  {
    "id": 79,
    "name": "Rivalité"
  },
  {
    "id": 80,
    "name": "Impassible"
  },
  {
    "id": 81,
    "name": "Rideau Neige"
  },
  {
    "id": 82,
    "name": "Gloutonnerie"
  },
  {
    "id": 83,
    "name": "Colérique"
  },
  {
    "id": 84,
    "name": "Délestage"
  },
  {
    "id": 85,
    "name": "Ignifugé"
  },
  {
    "id": 86,
    "name": "Simple"
  },
  {
    "id": 87,
    "name": "Peau Sèche"
  },
  {
    "id": 88,
    "name": "Télécharge"
  },
  {
    "id": 89,
    "name": "Poing de Fer"
  },
  {
    "id": 90,
    "name": "Soin Poison"
  },
  {
    "id": 91,
    "name": "Adaptabilité"
  },
  {
    "id": 92,
    "name": "Multi-Coups"
  },
  {
    "id": 93,
    "name": "Hydratation"
  },
  {
    "id": 94,
    "name": "Force Soleil"
  },
  {
    "id": 95,
    "name": "Pied Véloce"
  },
  {
    "id": 96,
    "name": "Normalise"
  },
  {
    "id": 97,
    "name": "Sniper"
  },
  {
    "id": 98,
    "name": "Garde Magik"
  },
  {
    "id": 99,
    "name": "Annule Garde"
  },
  {
    "id": 100,
    "name": "Frein"
  },
  {
    "id": 101,
    "name": "Technicien"
  },
  {
    "id": 102,
    "name": "Feuille Garde"
  },
  {
    "id": 103,
    "name": "Maladresse"
  },
  {
    "id": 104,
    "name": "Brise Moule"
  },
  {
    "id": 105,
    "name": "Chanceux"
  },
  {
    "id": 106,
    "name": "Boom Final"
  },
  {
    "id": 107,
    "name": "Anticipation"
  },
  {
    "id": 108,
    "name": "Prédiction"
  },
  {
    "id": 109,
    "name": "Inconscient"
  },
  {
    "id": 110,
    "name": "Lentiteintée"
  },
  {
    "id": 111,
    "name": "Filtre"
  },
  {
    "id": 112,
    "name": "Début Calme"
  },
  {
    "id": 113,
    "name": "Querelleur"
  },
  {
    "id": 114,
    "name": "Lavabo"
  },
  {
    "id": 115,
    "name": "Corps Gel"
  },
  {
    "id": 116,
    "name": "Solide Roc"
  },
  {
    "id": 117,
    "name": "Alerte Neige"
  },
  {
    "id": 118,
    "name": "Cherche Miel"
  },
  {
    "id": 119,
    "name": "Fouille"
  },
  {
    "id": 120,
    "name": "Téméraire"
  },
  {
    "id": 121,
    "name": "Multi-Type"
  },
  {
    "id": 122,
    "name": "Don Floral"
  },
  {
    "id": 123,
    "name": "Mauvais Rêve"
  },
  {
    "id": 124,
    "name": "Pickpocket"
  },
  {
    "id": 125,
    "name": "Sans Limite"
  },
  {
    "id": 126,
    "name": "Contestation"
  },
  {
    "id": 127,
    "name": "Tension"
  },
  {
    "id": 128,
    "name": "Acharné"
  },
  {
    "id": 129,
    "name": "Défaitiste"
  },
  {
    "id": 130,
    "name": "Corps Maudit"
  },
  {
    "id": 131,
    "name": "Cœur Soin"
  },
  {
    "id": 132,
    "name": "Garde-Ami"
  },
  {
    "id": 133,
    "name": "Armurouillée"
  },
  {
    "id": 134,
    "name": "Heavy Metal"
  },
  {
    "id": 135,
    "name": "Light Metal"
  },
  {
    "id": 136,
    "name": "Multiécaille"
  },
  {
    "id": 137,
    "name": "Rage Poison"
  },
  {
    "id": 138,
    "name": "Rage Brûlure"
  },
  {
    "id": 139,
    "name": "Récolte"
  },
  {
    "id": 140,
    "name": "Télépathe"
  },
  {
    "id": 141,
    "name": "Lunatique"
  },
  {
    "id": 142,
    "name": "Envelocape"
  },
  {
    "id": 143,
    "name": "Toxitouche"
  },
  {
    "id": 144,
    "name": "Régé-Force"
  },
  {
    "id": 145,
    "name": "Cœur de Coq"
  },
  {
    "id": 146,
    "name": "Baigne Sable"
  },
  {
    "id": 147,
    "name": "Peau Miracle"
  },
  {
    "id": 148,
    "name": "Analyste"
  },
  {
    "id": 149,
    "name": "Illusion"
  },
  {
    "id": 150,
    "name": "Imposteur"
  },
  {
    "id": 151,
    "name": "Infiltration"
  },
  {
    "id": 152,
    "name": "Momie"
  },
  {
    "id": 153,
    "name": "Impudence"
  },
  {
    "id": 154,
    "name": "Cœur Noble"
  },
  {
    "id": 155,
    "name": "Phobique"
  },
  {
    "id": 156,
    "name": "Miroir Magik"
  },
  {
    "id": 157,
    "name": "Herbivore"
  },
  {
    "id": 158,
    "name": "Farceur"
  },
  {
    "id": 159,
    "name": "Force Sable"
  },
  {
    "id": 160,
    "name": "Épine de Fer"
  },
  {
    "id": 161,
    "name": "Mode Transe"
  },
  {
    "id": 162,
    "name": "Victorieux"
  },
  {
    "id": 163,
    "name": "Turbo Brasier"
  },
  {
    "id": 164,
    "name": "Téra-Voltage"
  },
  {
    "id": 165,
    "name": "Aroma-Voile"
  },
  {
    "id": 166,
    "name": "Flora-Voile"
  },
  {
    "id": 167,
    "name": "Bajoues"
  },
  {
    "id": 168,
    "name": "Protéen"
  },
  {
    "id": 169,
    "name": "Toison Épaisse"
  },
  {
    "id": 170,
    "name": "Magicien"
  },
  {
    "id": 171,
    "name": "Pare-Balles"
  },
  {
    "id": 172,
    "name": "Battant"
  },
  {
    "id": 173,
    "name": "Prognathe"
  },
  {
    "id": 174,
    "name": "Peau Gelée"
  },
  {
    "id": 175,
    "name": "Gluco-Voile"
  },
  {
    "id": 176,
    "name": "Déclic Tactique"
  },
  {
    "id": 177,
    "name": "Ailes Bourrasque"
  },
  {
    "id": 178,
    "name": "Méga Blaster"
  },
  {
    "id": 179,
    "name": "Toison Herbue"
  },
  {
    "id": 180,
    "name": "Symbiose"
  },
  {
    "id": 181,
    "name": "Griffe Dure"
  },
  {
    "id": 182,
    "name": "Peau Féérique"
  },
  {
    "id": 183,
    "name": "Poisseux"
  },
  {
    "id": 184,
    "name": "Peau Céleste"
  },
  {
    "id": 185,
    "name": "Amour Filial"
  },
  {
    "id": 186,
    "name": "Aura Ténébreuse"
  },
  {
    "id": 187,
    "name": "Aura Féérique"
  },
  {
    "id": 188,
    "name": "Aura Inversée"
  },
  {
    "id": 189,
    "name": "Mer Primaire"
  },
  {
    "id": 190,
    "name": "Terre Finale"
  },
  {
    "id": 191,
    "name": "Souffle Delta"
  },
  {
    "id": 192,
    "name": "Endurance"
  },
  {
    "id": 193,
    "name": "Escampette"
  },
  {
    "id": 194,
    "name": "Repli Tactique"
  },
  {
    "id": 195,
    "name": "Sable Humide"
  },
  {
    "id": 196,
    "name": "Cruauté"
  },
  {
    "id": 197,
    "name": "Bouclier-Carcan"
  },
  {
    "id": 198,
    "name": "Filature"
  },
  {
    "id": 199,
    "name": "Aquabulle"
  },
  {
    "id": 200,
    "name": "Expert Acier"
  },
  {
    "id": 201,
    "name": "Folle Furie"
  },
  {
    "id": 202,
    "name": "Chasse-Neige"
  },
  {
    "id": 203,
    "name": "Longue Portée"
  },
  {
    "id": 204,
    "name": "Hydrata-Son"
  },
  {
    "id": 205,
    "name": "Prioguérison"
  },
  {
    "id": 206,
    "name": "Peau Électrique"
  },
  {
    "id": 207,
    "name": "Surf Caudal"
  },
  {
    "id": 208,
    "name": "Banc"
  },
  {
    "id": 209,
    "name": "Fantômasque"
  },
  {
    "id": 210,
    "name": "Synergie"
  },
  {
    "id": 211,
    "name": "Rassemblement"
  },
  {
    "id": 212,
    "name": "Corrosion"
  },
  {
    "id": 213,
    "name": "Hypersommeil"
  },
  {
    "id": 214,
    "name": "Prestance Royale"
  },
  {
    "id": 215,
    "name": "Expuls’Organes"
  },
  {
    "id": 216,
    "name": "Danseuse"
  },
  {
    "id": 217,
    "name": "Batterie"
  },
  {
    "id": 218,
    "name": "Boule de Poils"
  },
  {
    "id": 219,
    "name": "Corps Coloré"
  },
  {
    "id": 220,
    "name": "Animacœur"
  },
  {
    "id": 221,
    "name": "Mèche Rebelle"
  },
  {
    "id": 222,
    "name": "Receveur"
  },
  {
    "id": 223,
    "name": "Osmose"
  },
  {
    "id": 224,
    "name": "Boost Chimère"
  },
  {
    "id": 225,
    "name": "Système Alpha"
  },
  {
    "id": 226,
    "name": "Créa-Élec"
  },
  {
    "id": 227,
    "name": "Créa-Psy"
  },
  {
    "id": 228,
    "name": "Créa-Brume"
  },
  {
    "id": 229,
    "name": "Créa-Herbe"
  },
  {
    "id": 230,
    "name": "Métallo-Garde"
  },
  {
    "id": 231,
    "name": "Spectro-Bouclier"
  },
  {
    "id": 232,
    "name": "Prisme-Armure"
  },
  {
    "id": 233,
    "name": "Cérébro-Force"
  },
  {
    "id": 234,
    "name": "Lame Indomptable"
  },
  {
    "id": 235,
    "name": "Égide Inflexible"
  },
  {
    "id": 236,
    "name": "Libéro"
  },
  {
    "id": 237,
    "name": "Ramasse Ball"
  },
  {
    "id": 238,
    "name": "Effilochage"
  },
  {
    "id": 239,
    "name": "Propulseur"
  },
  {
    "id": 240,
    "name": "Armure Miroir"
  },
  {
    "id": 241,
    "name": "Dégobage"
  },
  {
    "id": 242,
    "name": "Nerfs d’Acier"
  },
  {
    "id": 243,
    "name": "Turbine"
  },
  {
    "id": 244,
    "name": "Punk Rock"
  },
  {
    "id": 245,
    "name": "Expul’Sable"
  },
  {
    "id": 246,
    "name": "Écailles Glacées"
  },
  {
    "id": 247,
    "name": "Mûrissement"
  },
  {
    "id": 248,
    "name": "Tête de Gel"
  },
  {
    "id": 249,
    "name": "Cercle d’Énergie"
  },
  {
    "id": 250,
    "name": "Mimétisme"
  },
  {
    "id": 251,
    "name": "Brise-Barrière"
  },
  {
    "id": 252,
    "name": "Boost Acier"
  },
  {
    "id": 253,
    "name": "Corps Condamné"
  },
  {
    "id": 254,
    "name": "Âme Vagabonde"
  },
  {
    "id": 255,
    "name": "Entêtement"
  },
  {
    "id": 256,
    "name": "Gaz Inhibiteur"
  },
  {
    "id": 257,
    "name": "Voile Pastel"
  },
  {
    "id": 258,
    "name": "Déclic Fringale"
  },
  {
    "id": 259,
    "name": "Tir Vif"
  },
  {
    "id": 260,
    "name": "Poing Invisible"
  },
  {
    "id": 261,
    "name": "Breuvage Suspect"
  },
  {
    "id": 262,
    "name": "Transistor"
  },
  {
    "id": 263,
    "name": "Dent de Dragon"
  },
  {
    "id": 264,
    "name": "Blanche Ruade"
  },
  {
    "id": 265,
    "name": "Sombre Ruade"
  },
  {
    "id": 266,
    "name": "Osmose Équine"
  },
  {
    "id": 267,
    "name": "Osmose Équine"
  },
  {
    "id": 268,
    "name": "Odeur Tenace"
  },
  {
    "id": 269,
    "name": "Semencier"
  },
  {
    "id": 270,
    "name": "Thermodynamique"
  },
  {
    "id": 271,
    "name": "Courroupace"
  },
  {
    "id": 272,
    "name": "Sel Purificateur"
  },
  {
    "id": 273,
    "name": "Bien Cuit"
  },
  {
    "id": 274,
    "name": "Aéroporté"
  },
  {
    "id": 275,
    "name": "Chien de Garde"
  },
  {
    "id": 276,
    "name": "Porte-Roche"
  },
  {
    "id": 277,
    "name": "Turbine Éolienne"
  },
  {
    "id": 278,
    "name": "Supermutation"
  },
  {
    "id": 279,
    "name": "Commandant"
  },
  {
    "id": 280,
    "name": "Grecharge"
  },
  {
    "id": 281,
    "name": "Paléosynthèse"
  },
  {
    "id": 282,
    "name": "Charge Quantique"
  },
  {
    "id": 283,
    "name": "Corps en Or"
  },
  {
    "id": 284,
    "name": "Urne du Fléau"
  },
  {
    "id": 285,
    "name": "Épée du Fléau"
  },
  {
    "id": 286,
    "name": "Bois du Fléau"
  },
  {
    "id": 287,
    "name": "Perles du Fléau"
  },
  {
    "id": 288,
    "name": "Pouls Orichalque"
  },
  {
    "id": 289,
    "name": "Moteur à Hadrons"
  },
  {
    "id": 290,
    "name": "Opportuniste"
  },
  {
    "id": 291,
    "name": "Ruminant"
  },
  {
    "id": 292,
    "name": "Incisif"
  },
  {
    "id": 293,
    "name": "Général Suprême"
  },
  {
    "id": 294,
    "name": "Collab"
  },
  {
    "id": 295,
    "name": "Dépôt Toxique"
  },
  {
    "id": 296,
    "name": "Armure Caudale"
  },
  {
    "id": 297,
    "name": "Absorbe-Terre"
  },
  {
    "id": 298,
    "name": "Force Fongique"
  },
  {
    "id": 299,
    "name": "Œil Révélateur"
  },
  {
    "id": 300,
    "name": "Nectar Mielleux"
  },
  {
    "id": 301,
    "name": "Aux Petits Soins"
  },
  {
    "id": 302,
    "name": "Chaîne Toxique"
  },
  {
    "id": 303,
    "name": "Force Mémorielle"
  },
  {
    "id": 304,
    "name": "Téramorphose"
  },
  {
    "id": 305,
    "name": "Téra-Carapace"
  },
  {
    "id": 306,
    "name": "Téraformation 0"
  },
  {
    "id": 307,
    "name": "Emprise Toxique"
  },
  {
    "id": 10001,
    "name": "mountaineer"
  },
  {
    "id": 10002,
    "name": "wave-rider"
  },
  {
    "id": 10003,
    "name": "skater"
  },
  {
    "id": 10004,
    "name": "thrust"
  },
  {
    "id": 10005,
    "name": "perception"
  },
  {
    "id": 10006,
    "name": "parry"
  },
  {
    "id": 10007,
    "name": "instinct"
  },
  {
    "id": 10008,
    "name": "dodge"
  },
  {
    "id": 10009,
    "name": "jagged-edge"
  },
  {
    "id": 10010,
    "name": "frostbite"
  },
  {
    "id": 10011,
    "name": "tenacity"
  },
  {
    "id": 10012,
    "name": "pride"
  },
  {
    "id": 10013,
    "name": "deep-sleep"
  },
  {
    "id": 10014,
    "name": "power-nap"
  },
  {
    "id": 10015,
    "name": "spirit"
  },
  {
    "id": 10016,
    "name": "warm-blanket"
  },
  {
    "id": 10017,
    "name": "gulp"
  },
  {
    "id": 10018,
    "name": "herbivore"
  },
  {
    "id": 10019,
    "name": "sandpit"
  },
  {
    "id": 10020,
    "name": "hot-blooded"
  },
  {
    "id": 10021,
    "name": "medic"
  },
  {
    "id": 10022,
    "name": "life-force"
  },
  {
    "id": 10023,
    "name": "lunchbox"
  },
  {
    "id": 10024,
    "name": "nurse"
  },
  {
    "id": 10025,
    "name": "melee"
  },
  {
    "id": 10026,
    "name": "sponge"
  },
  {
    "id": 10027,
    "name": "bodyguard"
  },
  {
    "id": 10028,
    "name": "hero"
  },
  {
    "id": 10029,
    "name": "last-bastion"
  },
  {
    "id": 10030,
    "name": "stealth"
  },
  {
    "id": 10031,
    "name": "vanguard"
  },
  {
    "id": 10032,
    "name": "nomad"
  },
  {
    "id": 10033,
    "name": "sequence"
  },
  {
    "id": 10034,
    "name": "grass-cloak"
  },
  {
    "id": 10035,
    "name": "celebrate"
  },
  {
    "id": 10036,
    "name": "lullaby"
  },
  {
    "id": 10037,
    "name": "calming"
  },
  {
    "id": 10038,
    "name": "daze"
  },
  {
    "id": 10039,
    "name": "frighten"
  },
  {
    "id": 10040,
    "name": "interference"
  },
  {
    "id": 10041,
    "name": "mood-maker"
  },
  {
    "id": 10042,
    "name": "confidence"
  },
  {
    "id": 10043,
    "name": "fortune"
  },
  {
    "id": 10044,
    "name": "bonanza"
  },
  {
    "id": 10045,
    "name": "explode"
  },
  {
    "id": 10046,
    "name": "omnipotent"
  },
  {
    "id": 10047,
    "name": "share"
  },
  {
    "id": 10048,
    "name": "black-hole"
  },
  {
    "id": 10049,
    "name": "shadow-dash"
  },
  {
    "id": 10050,
    "name": "sprint"
  },
  {
    "id": 10051,
    "name": "disgust"
  },
  {
    "id": 10052,
    "name": "high-rise"
  },
  {
    "id": 10053,
    "name": "climber"
  },
  {
    "id": 10054,
    "name": "flame-boost"
  },
  {
    "id": 10055,
    "name": "aqua-boost"
  },
  {
    "id": 10056,
    "name": "run-up"
  },
  {
    "id": 10057,
    "name": "conqueror"
  },
  {
    "id": 10058,
    "name": "shackle"
  },
  {
    "id": 10059,
    "name": "decoy"
  },
  {
    "id": 10060,
    "name": "shield"
  }
]